LICENSE
MANIFEST.in
README.md
setup.py
dat/__init__.py
dat/api/__init__.py
dat/api/build_api.py
dat/api/document_api.py
dat/api/new_api.py
dat/api/release_api.py
dat/api/run_api.py
dat/api/test_api.py
dat/conan/__init__.py
dat/conan/conan_handler.py
dat/conan/conanfile_template
dat/conan/extensions/__init__.py
dat/conan/extensions/build.py
dat/conan/extensions/package.py
dat/conan/extensions/test.py
dat/conan/test_package/__init__.py
dat/conan/test_package/conanfile.py
dat/core/__init__.py
dat/core/conf_reader.py
dat/errors/__init__.py
dat/errors/dat_exception.py
dat/scripts/__init__.py
dat/scripts/cli.py
dat/templates/basic.yml
dat/templates/bazel_hello.yml
dat/utils/__init__.py
dat/utils/dat_logger.py
dat/utils/replacements.py
dat/utils/utils.py
dat_build.egg-info/PKG-INFO
dat_build.egg-info/SOURCES.txt
dat_build.egg-info/dependency_links.txt
dat_build.egg-info/entry_points.txt
dat_build.egg-info/requires.txt
dat_build.egg-info/top_level.txt