Metadata-Version: 2.1
Name: dat-build
Version: 1.2.6
Summary: Package generator for C/C++ projects.
Home-page: https://github.com/demorgan104/dat
Author: demorgan104
Author-email: honestertech@protonmail.com
License: UNKNOWN
Platform: UNKNOWN
Classifier: Programming Language :: Python :: 3
Classifier: License :: OSI Approved :: MIT License
Classifier: Operating System :: OS Independent
Requires-Python: >=3.6
License-File: LICENSE
